hivebox/__init__.py
hivebox/common/__init__.py
hivebox/performance/__init__.py
hivebox/scripts/__init__.py
hivebox/scripts/collect.py
hivebox/scripts/live.py
hivebox/storage/__init__.py
hivebox-2.3.1.dist-info/LICENSE
hivebox-2.3.1.dist-info/METADATA
hivebox-2.3.1.dist-info/WHEEL
hivebox-2.3.1.dist-info/entry_points.txt
hivebox-2.3.1.dist-info/RECORD
