Metadata-Version: 2.1
Name: hivebox
Version: 2.3.1
Summary: HiveBox is a toolset helping in AI/ML/CV and other tasks
License: Proprietary
Author: HiveCV
Author-email: lukasz@hivecv.com
Requires-Python: >=3.9,<4.0
Classifier: License :: Other/Proprietary License
Classifier: Programming Language :: Python :: 3
Classifier: Programming Language :: Python :: 3.9
Classifier: Programming Language :: Python :: 3.10
Classifier: Programming Language :: Python :: 3.11
Classifier: Programming Language :: Python :: 3.12
Classifier: Programming Language :: Python :: 3.13
Requires-Dist: depthai (>=2.24)
Requires-Dist: numpy (>=1.21,<2.0)
Requires-Dist: opencv-contrib-python (>4)
Requires-Dist: opencv-python (>4)
Requires-Dist: requests (>=2.27,<3.0)
